tweetbench/__init__.py
tweetbench/__main__.py
tweetbench/py.typed
tweetbench-0.0.0.dist-info/entry_points.txt
tweetbench-0.0.0.dist-info/LICENSE
tweetbench-0.0.0.dist-info/WHEEL
tweetbench-0.0.0.dist-info/METADATA
tweetbench-0.0.0.dist-info/RECORD
